{
  "_id": {
    "$oid": "64d0d220a649a8d4f134c722"
  },
  "phoneNumber": "92205730",
  "emailAddresses": [
    "william@triviumcapital.tech"
  ],
  "isPhoneNumberVerified": true,
  "isEmailAddressVerified": false,
  "isActive": true,
  "isBlocked": false,
  "wrongPinAttempt": 0,
  "pin": "$2a$12$xuksvCNZMuAgtOFCZqep5Ok5Ixw/TTFmrzhaTiV.lc0nT/nPXqJD2",
  "callFirstName": "William ",
  "callLastName": "Haw",
  "dialCode": "+65",
  "metaData": {
    "hasShownVerifiedEmailSnackbar": true,
    "isAdminCreated": false,
    "isFirstTimeAccess": false
  },
  "isRequestAccountDeletion": false,
  "createdAt": {
    "$date": "2023-08-07T11:14:40.634Z"
  },
  "updatedAt": {
    "$date": "2023-09-13T08:02:16.322Z"
  },
  "__v": 0
}